MANIFEST.in
README
setup.py
basket/__init__.py
basket/admin.py
basket/forms.py
basket/middleware.py
basket/models.py
basket/settings.py
basket/signals.py
basket/urls.py
basket/utils.py
basket/views.py
basket/contrib/__init__.py
basket/contrib/orderinfo/__init__.py
basket/contrib/orderinfo/admin.py
basket/contrib/orderinfo/forms.py
basket/contrib/orderinfo/models.py
basket/locale/ru/LC_MESSAGES/django.mo
basket/static/basket/img/ajax-loader.gif
basket/static/basket/js/basket.js
basket/static/basket/js/jquery-1.4.2.min.js
basket/templates/admin/basket/order/change_form.html
basket/templates/basket/base.html
basket/templates/basket/basket.html
basket/templates/basket/button.html
basket/templates/basket/confirm.html
basket/templates/basket/delete-script.js
basket/templates/basket/empty.html
basket/templates/basket/panel.html
basket/templates/basket/summary.html
basket/templates/basket/thankyou.html
basket/templatetags/__init__.py
basket/templatetags/basket_tags.py
django_basket.egg-info/PKG-INFO
django_basket.egg-info/SOURCES.txt
django_basket.egg-info/dependency_links.txt
django_basket.egg-info/not-zip-safe
django_basket.egg-info/requires.txt
django_basket.egg-info/top_level.txt