Metadata-Version: 1.1
Name: django-basket
Version: 0.4.5
Summary: Django generic basket application. Allow to put in basket any object and view orders in the Django admin interface
